src/__init__.py
src/inf.py
src/starterpack.py
metapaths-1.0.0.dist-info/METADATA
metapaths-1.0.0.dist-info/WHEEL
metapaths-1.0.0.dist-info/top_level.txt
metapaths-1.0.0.dist-info/RECORD
